whatsapp_chat_analyze/__init__.py
whatsapp_chat_analyze/cli.py
whatsapp_chat_analyze-0.1.7.dist-info/METADATA
whatsapp_chat_analyze-0.1.7.dist-info/WHEEL
whatsapp_chat_analyze-0.1.7.dist-info/entry_points.txt
whatsapp_chat_analyze-0.1.7.dist-info/RECORD
